lookout_mra_client/__init__.py
lookout_mra_client/lookout_logger.py
lookout_mra_client/mra_client.py
lookout_mra_client/mra_event_runner.py
lookout_mra_client/mra_v2_stream.py
lookout_mra_client/mra_v2_stream_thread.py
lookout_mra_client/oauth2_client.py
lookout_mra_client/oauth_client.py
lookout_mra_client/server_sent_event.py
lookout_mra_client/sse_client.py
lookout_mra_client/syslog_client.py
lookout_mra_client/event_forwarders/__init__.py
lookout_mra_client/event_forwarders/event_forwarder.py
lookout_mra_client/event_forwarders/qradar_event_forwarder.py
lookout_mra_client/event_forwarders/splunk_event_forwarder.py
lookout_mra_client/event_store/__init__.py
lookout_mra_client/event_store/event_store.py
lookout_mra_client/event_store/file_event_store.py
lookout_mra_client/event_translators/__init__.py
lookout_mra_client/event_translators/leef_translator.py
lookout_mra_client/event_translators/mra_v1_leef_mapping.py
lookout_mra_client/event_translators/mra_v2_leef_mapping.py
lookout_mra_client/event_translators/utilities.py
lookout_mra_client/models/__init__.py
lookout_mra_client/models/base_model.py
lookout_mra_client/models/configuration.py
lookout_mra_client/models/form_submission.py
lookout_mra_client/scripts/mra_v2_demo_script.py
lookout_mra_client-2.6.6.dist-info/licenses/LICENSE.txt
lookout_mra_client-2.6.6.dist-info/METADATA
lookout_mra_client-2.6.6.dist-info/WHEEL
lookout_mra_client-2.6.6.dist-info/entry_points.txt
lookout_mra_client-2.6.6.dist-info/top_level.txt
lookout_mra_client-2.6.6.dist-info/RECORD
