Metadata-Version: 2.4
Name: lookout_mra_client
Version: 2.6.6
Summary: Lookout's Mobile Risk API in Python
Author-email: Lookout <esupport@lookout.com>
Classifier: Development Status :: 5 - Production/Stable
Classifier: License :: OSI Approved :: MIT License
Classifier: Programming Language :: Python :: 3.9
Requires-Python: >=3.6
License-File: LICENSE.txt
Requires-Dist: requests
Requires-Dist: oauthlib>=3.2
Requires-Dist: requests-oauthlib>=1.3
Provides-Extra: models
Requires-Dist: peewee>=3.15; extra == "models"
Requires-Dist: wtforms>=3.0; extra == "models"
Requires-Dist: flask_wtf>=1.0; extra == "models"
Requires-Dist: furl>=2.1; extra == "models"
Dynamic: license-file
